firebase_agent/__init__.py
firebase_agent/config.py
firebase_agent/entity.py
firebase_agent/main.py
firebase_agent-0.3.2.dist-info/LICENSE
firebase_agent-0.3.2.dist-info/METADATA
firebase_agent-0.3.2.dist-info/WHEEL
firebase_agent-0.3.2.dist-info/RECORD
