Metadata-Version: 2.1
Name: firebase-agent
Version: 0.3.2
Summary: 
Author: gab25
Author-email: gabrielesorci.25@gmail.com
Requires-Python: >=3.11,<4.0
Classifier: Programming Language :: Python :: 3
Classifier: Programming Language :: Python :: 3.11
Classifier: Programming Language :: Python :: 3.12
Requires-Dist: firebase-admin (>=6.4.0,<7.0.0)
Requires-Dist: numpy (>=1.26.4,<2.0.0)
Requires-Dist: requests (>=2.31.0,<3.0.0)
